{".class": "MypyFile", "_fullname": "cleanPony.core.paginated_result", "is_partial_stub_package": false, "is_stub": false, "names": {".class": "SymbolTable", "Entity": {".class": "SymbolTableNode", "cross_ref": "cleanPony.core.entities.Entity", "kind": "Gdef"}, "List": {".class": "SymbolTableNode", "cross_ref": "typing.List", "kind": "Gdef"}, "PaginatedResult": {".class": "SymbolTableNode", "kind": "Gdef", "node": {".class": "TypeInfo", "_promote": null, "abstract_attributes": [], "bases": ["builtins.object"], "declared_metaclass": null, "defn": {".class": "ClassDef", "fullname": "cleanPony.core.paginated_result.PaginatedResult", "name": "PaginatedResult", "type_vars": []}, "flags": [], "fullname": "cleanPony.core.paginated_result.PaginatedResult", "metaclass_type": null, "metadata": {"dataclass": {"attributes": {"items": {"column": 4, "has_default": true, "is_in_init": true, "is_init_var": false, "line": 8, "name": "items"}, "page": {"column": 4, "has_default": true, "is_in_init": true, "is_init_var": false, "line": 9, "name": "page"}, "page_size": {"column": 4, "has_default": true, "is_in_init": true, "is_init_var": false, "line": 10, "name": "page_size"}}, "frozen": true}}, "module_name": "cleanPony.core.paginated_result", "mro": ["cleanPony.core.paginated_result.PaginatedResult", "builtins.object"], "names": {".class": "SymbolTable", "__init__": {".class": "SymbolTableNode", "kind": "Mdef", "node": {".class": "FuncDef", "arg_kinds": [0, 1, 1, 1], "arg_names": ["self", "items", "page", "page_size"], "flags": [], "fullname": "cleanPony.core.paginated_result.PaginatedResult.__init__", "name": "__init__", "type": {".class": "CallableType", "arg_kinds": [0, 1, 1, 1], "arg_names": ["self", "items", "page", "page_size"], "arg_types": ["cleanPony.core.paginated_result.PaginatedResult", {".class": "Instance", "args": ["cleanPony.core.entities.Entity"], "type_ref": "builtins.list"}, "builtins.int", "builtins.int"], "bound_args": [], "def_extras": {}, "fallback": "builtins.function", "implicit": false, "is_ellipsis_args": false, "name": "__init__ of PaginatedResult", "ret_type": {".class": "NoneTyp"}, "variables": []}}, "plugin_generated": true}, "items": {".class": "SymbolTableNode", "kind": "Mdef", "node": {".class": "Var", "flags": ["is_initialized_in_class", "is_property"], "fullname": "cleanPony.core.paginated_result.PaginatedResult.items", "name": "items", "type": {".class": "Instance", "args": ["cleanPony.core.entities.Entity"], "type_ref": "builtins.list"}}}, "page": {".class": "SymbolTableNode", "kind": "Mdef", "node": {".class": "Var", "flags": ["is_initialized_in_class", "is_property"], "fullname": "cleanPony.core.paginated_result.PaginatedResult.page", "name": "page", "type": "builtins.int"}}, "page_size": {".class": "SymbolTableNode", "kind": "Mdef", "node": {".class": "Var", "flags": ["is_initialized_in_class", "is_property"], "fullname": "cleanPony.core.paginated_result.PaginatedResult.page_size", "name": "page_size", "type": "builtins.int"}}}, "tuple_type": null, "type_vars": [], "typeddict_type": null}}, "__doc__": {".class": "SymbolTableNode", "kind": "Gdef", "node": {".class": "Var", "flags": [], "fullname": "cleanPony.core.paginated_result.__doc__", "name": "__doc__", "type": "builtins.str"}}, "__file__": {".class": "SymbolTableNode", "kind": "Gdef", "node": {".class": "Var", "flags": [], "fullname": "cleanPony.core.paginated_result.__file__", "name": "__file__", "type": "builtins.str"}}, "__name__": {".class": "SymbolTableNode", "kind": "Gdef", "node": {".class": "Var", "flags": [], "fullname": "cleanPony.core.paginated_result.__name__", "name": "__name__", "type": "builtins.str"}}, "__package__": {".class": "SymbolTableNode", "kind": "Gdef", "node": {".class": "Var", "flags": [], "fullname": "cleanPony.core.paginated_result.__package__", "name": "__package__", "type": "builtins.str"}}, "dataclass": {".class": "SymbolTableNode", "cross_ref": "dataclasses.dataclass", "kind": "Gdef"}, "field": {".class": "SymbolTableNode", "cross_ref": "dataclasses.field", "kind": "Gdef"}}, "path": "/home/danzaw/projects/cleanPony/cleanPony/core/paginated_result.py"}