{".class": "MypyFile", "_fullname": "cleanPony.core.actions.base.get", "is_partial_stub_package": false, "is_stub": false, "names": {".class": "SymbolTable", "ActionBase": {".class": "SymbolTableNode", "cross_ref": "cleanPony.core.actions.action_base.ActionBase", "kind": "Gdef"}, "CrudRepository": {".class": "SymbolTableNode", "cross_ref": "cleanPony.core.repositories.CrudRepository", "kind": "Gdef"}, "GetEntity": {".class": "SymbolTableNode", "kind": "Gdef", "node": {".class": "TypeInfo", "_promote": null, "abstract_attributes": [], "bases": ["cleanPony.core.actions.action_base.ActionBase"], "declared_metaclass": null, "defn": {".class": "ClassDef", "fullname": "cleanPony.core.actions.base.get.GetEntity", "name": "GetEntity", "type_vars": []}, "flags": [], "fullname": "cleanPony.core.actions.base.get.GetEntity", "metaclass_type": null, "metadata": {}, "module_name": "cleanPony.core.actions.base.get", "mro": ["cleanPony.core.actions.base.get.GetEntity", "cleanPony.core.actions.action_base.ActionBase", "builtins.object"], "names": {".class": "SymbolTable", "__init__": {".class": "SymbolTableNode", "kind": "Mdef", "node": {".class": "FuncDef", "arg_kinds": [0, 0], "arg_names": ["self", "repository"], "flags": [], "fullname": "cleanPony.core.actions.base.get.GetEntity.__init__", "name": "__init__", "type": {".class": "CallableType", "arg_kinds": [0, 0], "arg_names": ["self", "repository"], "arg_types": ["cleanPony.core.actions.base.get.GetEntity", "cleanPony.core.repositories.CrudRepository"], "bound_args": [], "def_extras": {"first_arg": "self"}, "fallback": "builtins.function", "implicit": false, "is_ellipsis_args": false, "name": "__init__ of GetEntity", "ret_type": {".class": "NoneTyp"}, "variables": []}}}, "process": {".class": "SymbolTableNode", "kind": "Mdef", "node": {".class": "FuncDef", "arg_kinds": [0, 0], "arg_names": ["self", "request"], "flags": [], "fullname": "cleanPony.core.actions.base.get.GetEntity.process", "name": "process", "type": null}}, "repository": {".class": "SymbolTableNode", "implicit": true, "kind": "Mdef", "node": {".class": "Var", "flags": [], "fullname": "cleanPony.core.actions.base.get.GetEntity.repository", "name": "repository", "type": "cleanPony.core.repositories.CrudRepository"}}}, "tuple_type": null, "type_vars": [], "typeddict_type": null}}, "GetEntityRequest": {".class": "SymbolTableNode", "kind": "Gdef", "node": {".class": "TypeInfo", "_promote": null, "abstract_attributes": [], "bases": ["builtins.object"], "declared_metaclass": null, "defn": {".class": "ClassDef", "fullname": "cleanPony.core.actions.base.get.GetEntityRequest", "name": "GetEntityRequest", "type_vars": []}, "flags": [], "fullname": "cleanPony.core.actions.base.get.GetEntityRequest", "metaclass_type": null, "metadata": {"dataclass": {"attributes": {"id": {"column": 4, "has_default": false, "is_in_init": true, "is_init_var": false, "line": 9, "name": "id"}}, "frozen": true}}, "module_name": "cleanPony.core.actions.base.get", "mro": ["cleanPony.core.actions.base.get.GetEntityRequest", "builtins.object"], "names": {".class": "SymbolTable", "__init__": {".class": "SymbolTableNode", "kind": "Mdef", "node": {".class": "FuncDef", "arg_kinds": [0, 0], "arg_names": ["self", "id"], "flags": [], "fullname": "cleanPony.core.actions.base.get.GetEntityRequest.__init__", "name": "__init__", "type": {".class": "CallableType", "arg_kinds": [0, 0], "arg_names": ["self", "id"], "arg_types": ["cleanPony.core.actions.base.get.GetEntityRequest", "builtins.int"], "bound_args": [], "def_extras": {}, "fallback": "builtins.function", "implicit": false, "is_ellipsis_args": false, "name": "__init__ of GetEntityRequest", "ret_type": {".class": "NoneTyp"}, "variables": []}}, "plugin_generated": true}, "id": {".class": "SymbolTableNode", "kind": "Mdef", "node": {".class": "Var", "flags": ["is_initialized_in_class", "is_property"], "fullname": "cleanPony.core.actions.base.get.GetEntityRequest.id", "name": "id", "type": "builtins.int"}}}, "tuple_type": null, "type_vars": [], "typeddict_type": null}}, "IdValidator": {".class": "SymbolTableNode", "cross_ref": "cleanPony.core.validators.id_validator.IdValidator", "kind": "Gdef"}, "__doc__": {".class": "SymbolTableNode", "kind": "Gdef", "node": {".class": "Var", "flags": [], "fullname": "cleanPony.core.actions.base.get.__doc__", "name": "__doc__", "type": "builtins.str"}}, "__file__": {".class": "SymbolTableNode", "kind": "Gdef", "node": {".class": "Var", "flags": [], "fullname": "cleanPony.core.actions.base.get.__file__", "name": "__file__", "type": "builtins.str"}}, "__name__": {".class": "SymbolTableNode", "kind": "Gdef", "node": {".class": "Var", "flags": [], "fullname": "cleanPony.core.actions.base.get.__name__", "name": "__name__", "type": "builtins.str"}}, "__package__": {".class": "SymbolTableNode", "kind": "Gdef", "node": {".class": "Var", "flags": [], "fullname": "cleanPony.core.actions.base.get.__package__", "name": "__package__", "type": "builtins.str"}}, "dataclass": {".class": "SymbolTableNode", "cross_ref": "dataclasses.dataclass", "kind": "Gdef"}}, "path": "cleanPony/core/actions/base/get.py"}